llm_horde/__init__.py
llm_horde/horde_request.py
llm_horde/llm_horde.py
llm_horde/templates.json
llm_horde-0.5.dist-info/LICENSE
llm_horde-0.5.dist-info/METADATA
llm_horde-0.5.dist-info/WHEEL
llm_horde-0.5.dist-info/entry_points.txt
llm_horde-0.5.dist-info/top_level.txt
llm_horde-0.5.dist-info/RECORD
