Metadata-Version: 2.1
Name: llm-horde
Version: 0.5
Summary: Plugin for LLM adding models hosted on AI Horde
Author: spinagon
License: Apache-2.0
Project-URL: Homepage, https://github.com/spinagon/llm-horde
Project-URL: Changelog, https://github.com/spinagon/llm-horde/releases
Project-URL: Issues, https://github.com/spinagon/llm-horde/issues
Classifier: License :: OSI Approved :: Apache Software License
License-File: LICENSE
Requires-Dist: llm
Requires-Dist: requests
